src/__init__.py
src/fuzzler.py
fuzzler-1.0.1.dist-info/METADATA
fuzzler-1.0.1.dist-info/WHEEL
fuzzler-1.0.1.dist-info/licenses/LICENSE
fuzzler-1.0.1.dist-info/RECORD
