Metadata-Version: 2.1
Name: Fuzzler
Version: 1.0.1
Summary: Create tailored password lists from webpages using AI/NLP
Project-URL: Homepage, https://github.com/suffs811/fuzzler
Project-URL: Bug Tracker, https://github.com/suffs811/fuzzler/issues
Author-email: Tanner Smith <suffi811@outlook.com>
License-File: LICENSE
Classifier: License :: OSI Approved :: MIT License
Classifier: Operating System :: Unix
Classifier: Programming Language :: Python :: 3
Requires-Python: >=3.7
